{"car":[[{"x":69,"y":181},{"x":71,"y":181},{"x":73,"y":181},{"x":74,"y":181},{"x":76,"y":181},{"x":77,"y":181},{"x":79,"y":180},{"x":80,"y":180},{"x":81,"y":180},{"x":82,"y":180},{"x":83,"y":180},{"x":84,"y":180},{"x":85,"y":180},{"x":87,"y":180},{"x":87,"y":179},{"x":88,"y":179},{"x":91,"y":179},{"x":92,"y":179},{"x":94,"y":179},{"x":95,"y":179},{"x":97,"y":179},{"x":99,"y":179},{"x":100,"y":179},{"x":102,"y":179},{"x":103,"y":179},{"x":105,"y":179},{"x":106,"y":179},{"x":108,"y":179},{"x":109,"y":179},{"x":110,"y":179},{"x":111,"y":179},{"x":113,"y":179},{"x":114,"y":179},{"x":115,"y":179},{"x":116,"y":179},{"x":118,"y":179},{"x":119,"y":179},{"x":121,"y":179},{"x":122,"y":179},{"x":123,"y":179},{"x":124,"y":179},{"x":126,"y":179},{"x":127,"y":179},{"x":128,"y":179},{"x":129,"y":179},{"x":131,"y":179},{"x":132,"y":179},{"x":132,"y":178},{"x":133,"y":178},{"x":134,"y":177},{"x":137,"y":174},{"x":139,"y":171},{"x":143,"y":169},{"x":145,"y":165},{"x":147,"y":163},{"x":149,"y":161},{"x":152,"y":159},{"x":154,"y":157},{"x":156,"y":154},{"x":158,"y":153},{"x":161,"y":151},{"x":164,"y":147},{"x":166,"y":145},{"x":169,"y":142},{"x":171,"y":141},{"x":173,"y":139},{"x":175,"y":137},{"x":176,"y":136},{"x":178,"y":133},{"x":181,"y":132},{"x":182,"y":130},{"x":185,"y":127},{"x":186,"y":126},{"x":187,"y":125},{"x":188,"y":123},{"x":189,"y":122},{"x":190,"y":121},{"x":191,"y":120},{"x":192,"y":119},{"x":193,"y":117},{"x":194,"y":116},{"x":195,"y":114},{"x":196,"y":113},{"x":198,"y":112},{"x":199,"y":111},{"x":200,"y":109},{"x":201,"y":109},{"x":202,"y":108},{"x":202,"y":107},{"x":203,"y":107},{"x":203,"y":106},{"x":206,"y":106},{"x":209,"y":106},{"x":211,"y":107},{"x":214,"y":107},{"x":216,"y":107},{"x":220,"y":107},{"x":223,"y":107},{"x":227,"y":107},{"x":232,"y":108},{"x":236,"y":109},{"x":240,"y":109},{"x":242,"y":110},{"x":244,"y":110},{"x":245,"y":111},{"x":246,"y":111},{"x":248,"y":111},{"x":250,"y":111},{"x":251,"y":111},{"x":253,"y":111},{"x":254,"y":112},{"x":255,"y":112},{"x":257,"y":112},{"x":261,"y":113},{"x":263,"y":113},{"x":266,"y":113},{"x":269,"y":113},{"x":271,"y":114},{"x":273,"y":114},{"x":274,"y":114},{"x":277,"y":115},{"x":278,"y":115},{"x":280,"y":115},{"x":281,"y":115},{"x":282,"y":115},{"x":283,"y":115},{"x":284,"y":115},{"x":285,"y":115},{"x":287,"y":115},{"x":289,"y":114},{"x":291,"y":114},{"x":293,"y":113},{"x":294,"y":113},{"x":296,"y":113},{"x":297,"y":113},{"x":298,"y":113},{"x":299,"y":113},{"x":300,"y":113},{"x":301,"y":113},{"x":302,"y":113},{"x":303,"y":113},{"x":304,"y":113},{"x":305,"y":113},{"x":307,"y":113},{"x":308,"y":113},{"x":309,"y":113},{"x":310,"y":113},{"x":311,"y":113},{"x":311,"y":114},{"x":311,"y":115},{"x":311,"y":116},{"x":311,"y":118},{"x":311,"y":120},{"x":311,"y":122},{"x":311,"y":124},{"x":311,"y":127},{"x":311,"y":131},{"x":311,"y":134},{"x":311,"y":138},{"x":311,"y":142},{"x":311,"y":146},{"x":311,"y":149},{"x":311,"y":152},{"x":311,"y":155},{"x":311,"y":160},{"x":311,"y":164},{"x":313,"y":168},{"x":314,"y":174},{"x":315,"y":180},{"x":316,"y":184},{"x":317,"y":187},{"x":317,"y":189},{"x":317,"y":191},{"x":317,"y":192},{"x":318,"y":194},{"x":318,"y":195},{"x":319,"y":196},{"x":322,"y":197},{"x":324,"y":197},{"x":326,"y":197},{"x":328,"y":198},{"x":330,"y":198},{"x":332,"y":199},{"x":334,"y":199},{"x":335,"y":199},{"x":337,"y":200},{"x":338,"y":200},{"x":340,"y":200},{"x":342,"y":200},{"x":342,"y":201},{"x":343,"y":201},{"x":344,"y":201},{"x":345,"y":201},{"x":346,"y":201},{"x":347,"y":202},{"x":349,"y":203},{"x":350,"y":203},{"x":351,"y":203},{"x":352,"y":203},{"x":353,"y":204},{"x":354,"y":204},{"x":355,"y":204},{"x":356,"y":205},{"x":357,"y":205},{"x":357,"y":206},{"x":358,"y":206},{"x":359,"y":206},{"x":360,"y":206},{"x":360,"y":207},{"x":361,"y":207},{"x":362,"y":207},{"x":363,"y":207},{"x":364,"y":207},{"x":365,"y":208},{"x":366,"y":208},{"x":368,"y":208},{"x":369,"y":208},{"x":369,"y":209},{"x":370,"y":209},{"x":371,"y":209},{"x":371,"y":210},{"x":372,"y":210},{"x":373,"y":210},{"x":374,"y":210},{"x":374,"y":213},{"x":372,"y":218},{"x":370,"y":222},{"x":369,"y":226},{"x":368,"y":231},{"x":367,"y":234},{"x":367,"y":236},{"x":366,"y":237},{"x":366,"y":239},{"x":366,"y":240},{"x":366,"y":241},{"x":366,"y":243},{"x":365,"y":244},{"x":365,"y":245},{"x":365,"y":246},{"x":365,"y":247},{"x":365,"y":248},{"x":365,"y":249},{"x":365,"y":251},{"x":365,"y":252},{"x":365,"y":253},{"x":365,"y":254},{"x":365,"y":255},{"x":365,"y":256},{"x":364,"y":256},{"x":364,"y":257},{"x":364,"y":258},{"x":364,"y":259},{"x":363,"y":260},{"x":362,"y":260},{"x":362,"y":262},{"x":362,"y":263},{"x":362,"y":264},{"x":362,"y":265},{"x":361,"y":265},{"x":361,"y":266},{"x":361,"y":267},{"x":361,"y":268},{"x":361,"y":269},{"x":360,"y":269},{"x":359,"y":269},{"x":358,"y":269},{"x":357,"y":269},{"x":356,"y":269},{"x":355,"y":269},{"x":354,"y":269},{"x":352,"y":269},{"x":350,"y":269},{"x":349,"y":269},{"x":347,"y":269},{"x":345,"y":269},{"x":343,"y":269},{"x":340,"y":269},{"x":337,"y":269},{"x":334,"y":269},{"x":331,"y":269},{"x":327,"y":269},{"x":324,"y":269},{"x":320,"y":269},{"x":315,"y":269},{"x":311,"y":269},{"x":308,"y":269},{"x":305,"y":269},{"x":304,"y":269},{"x":302,"y":269},{"x":301,"y":268},{"x":300,"y":268},{"x":299,"y":268},{"x":298,"y":268},{"x":297,"y":268},{"x":296,"y":268},{"x":295,"y":268},{"x":294,"y":268},{"x":293,"y":268},{"x":292,"y":268},{"x":291,"y":268},{"x":290,"y":267},{"x":290,"y":266},{"x":289,"y":266},{"x":289,"y":265},{"x":288,"y":265},{"x":288,"y":264},{"x":287,"y":264},{"x":287,"y":263},{"x":286,"y":262},{"x":285,"y":261},{"x":284,"y":260},{"x":283,"y":259},{"x":282,"y":258},{"x":281,"y":257},{"x":279,"y":255},{"x":278,"y":253},{"x":276,"y":253},{"x":275,"y":252},{"x":274,"y":251},{"x":273,"y":250},{"x":271,"y":249},{"x":270,"y":249},{"x":269,"y":248},{"x":267,"y":248},{"x":266,"y":247},{"x":264,"y":246},{"x":262,"y":245},{"x":260,"y":245},{"x":259,"y":244},{"x":258,"y":244},{"x":256,"y":244},{"x":255,"y":244},{"x":253,"y":244},{"x":252,"y":244},{"x":251,"y":244},{"x":249,"y":244},{"x":248,"y":244},{"x":246,"y":244},{"x":245,"y":244},{"x":243,"y":244},{"x":242,"y":244},{"x":240,"y":244},{"x":239,"y":244},{"x":238,"y":244},{"x":237,"y":244},{"x":236,"y":244},{"x":236,"y":245},{"x":235,"y":245},{"x":235,"y":246},{"x":235,"y":247},{"x":234,"y":247},{"x":234,"y":248},{"x":233,"y":248},{"x":233,"y":249},{"x":232,"y":250},{"x":232,"y":251},{"x":232,"y":252},{"x":231,"y":252},{"x":231,"y":253},{"x":231,"y":254},{"x":231,"y":255},{"x":230,"y":256},{"x":230,"y":258},{"x":230,"y":259},{"x":229,"y":260},{"x":229,"y":261},{"x":229,"y":262},{"x":226,"y":262},{"x":223,"y":262},{"x":220,"y":262},{"x":216,"y":262},{"x":211,"y":262},{"x":206,"y":261},{"x":201,"y":260},{"x":197,"y":259},{"x":192,"y":258},{"x":189,"y":258},{"x":187,"y":257},{"x":185,"y":257},{"x":184,"y":257},{"x":182,"y":257},{"x":182,"y":256},{"x":180,"y":256},{"x":179,"y":256},{"x":178,"y":256},{"x":177,"y":256},{"x":176,"y":256},{"x":175,"y":256},{"x":173,"y":256},{"x":172,"y":256},{"x":171,"y":256},{"x":170,"y":256},{"x":169,"y":256},{"x":168,"y":256},{"x":167,"y":256},{"x":166,"y":256},{"x":166,"y":255},{"x":165,"y":255},{"x":164,"y":255}],[{"x":163,"y":254},{"x":162,"y":253},{"x":162,"y":252},{"x":161,"y":251},{"x":161,"y":250},{"x":161,"y":249},{"x":160,"y":249},{"x":160,"y":248},{"x":159,"y":248},{"x":159,"y":246},{"x":158,"y":245},{"x":158,"y":244},{"x":157,"y":243},{"x":157,"y":242},{"x":157,"y":241},{"x":156,"y":241},{"x":155,"y":240},{"x":155,"y":239},{"x":155,"y":238},{"x":154,"y":238},{"x":154,"y":237},{"x":153,"y":237},{"x":153,"y":236},{"x":152,"y":235},{"x":151,"y":235},{"x":151,"y":234},{"x":150,"y":234},{"x":150,"y":233},{"x":149,"y":233},{"x":148,"y":232},{"x":147,"y":232},{"x":146,"y":232},{"x":146,"y":231},{"x":145,"y":231},{"x":144,"y":231},{"x":143,"y":231},{"x":142,"y":230},{"x":141,"y":230},{"x":140,"y":230},{"x":139,"y":230},{"x":138,"y":230},{"x":137,"y":230},{"x":136,"y":230},{"x":135,"y":230},{"x":134,"y":230},{"x":133,"y":230},{"x":132,"y":230},{"x":131,"y":230},{"x":130,"y":230},{"x":129,"y":230},{"x":128,"y":230},{"x":127,"y":230},{"x":126,"y":230},{"x":125,"y":230},{"x":124,"y":230},{"x":123,"y":230},{"x":123,"y":231},{"x":122,"y":231},{"x":121,"y":231},{"x":120,"y":232},{"x":119,"y":232},{"x":117,"y":233},{"x":116,"y":234},{"x":115,"y":235},{"x":114,"y":236},{"x":113,"y":237},{"x":112,"y":237},{"x":112,"y":238},{"x":110,"y":239},{"x":110,"y":240},{"x":108,"y":241},{"x":107,"y":242},{"x":107,"y":243},{"x":106,"y":243},{"x":106,"y":244},{"x":105,"y":244},{"x":104,"y":245},{"x":104,"y":246},{"x":103,"y":247},{"x":103,"y":248},{"x":102,"y":248},{"x":102,"y":249},{"x":101,"y":250},{"x":101,"y":251},{"x":100,"y":253},{"x":100,"y":254},{"x":99,"y":255},{"x":99,"y":256},{"x":98,"y":256},{"x":98,"y":257},{"x":98,"y":258},{"x":98,"y":259},{"x":97,"y":259},{"x":97,"y":260},{"x":97,"y":262},{"x":97,"y":263},{"x":96,"y":263},{"x":96,"y":264},{"x":96,"y":265},{"x":96,"y":266},{"x":95,"y":266},{"x":95,"y":267},{"x":95,"y":268},{"x":95,"y":269},{"x":95,"y":270},{"x":95,"y":271},{"x":95,"y":272},{"x":95,"y":273},{"x":95,"y":274},{"x":95,"y":275},{"x":95,"y":276},{"x":96,"y":278},{"x":99,"y":279},{"x":97,"y":278},{"x":96,"y":277},{"x":94,"y":275},{"x":93,"y":274},{"x":92,"y":273},{"x":91,"y":273},{"x":91,"y":272},{"x":90,"y":272},{"x":89,"y":271},{"x":89,"y":270},{"x":88,"y":270},{"x":87,"y":269},{"x":86,"y":269},{"x":86,"y":268},{"x":85,"y":268},{"x":84,"y":267},{"x":83,"y":266},{"x":82,"y":265},{"x":81,"y":265},{"x":81,"y":264},{"x":80,"y":264},{"x":79,"y":263},{"x":78,"y":262},{"x":77,"y":262},{"x":76,"y":262},{"x":75,"y":261},{"x":74,"y":261},{"x":73,"y":261},{"x":72,"y":261},{"x":71,"y":260},{"x":70,"y":260},{"x":69,"y":260},{"x":68,"y":259},{"x":67,"y":259},{"x":66,"y":259},{"x":65,"y":259},{"x":64,"y":259},{"x":63,"y":259},{"x":62,"y":259},{"x":61,"y":257},{"x":60,"y":254},{"x":59,"y":249},{"x":58,"y":245},{"x":58,"y":241},{"x":58,"y":237},{"x":57,"y":232},{"x":56,"y":228},{"x":55,"y":225},{"x":55,"y":222},{"x":54,"y":219},{"x":54,"y":216},{"x":54,"y":213},{"x":54,"y":211},{"x":54,"y":209},{"x":54,"y":207},{"x":54,"y":206},{"x":55,"y":204},{"x":55,"y":203},{"x":55,"y":202},{"x":55,"y":201},{"x":56,"y":199},{"x":56,"y":198},{"x":56,"y":197},{"x":56,"y":196},{"x":57,"y":195},{"x":57,"y":194},{"x":57,"y":193},{"x":57,"y":192},{"x":57,"y":191},{"x":57,"y":190},{"x":57,"y":189},{"x":57,"y":188},{"x":58,"y":188},{"x":58,"y":187},{"x":59,"y":187},{"x":60,"y":186},{"x":61,"y":186},{"x":61,"y":185},{"x":62,"y":185},{"x":63,"y":185},{"x":64,"y":185},{"x":64,"y":184},{"x":65,"y":184},{"x":66,"y":184},{"x":67,"y":184},{"x":68,"y":184},{"x":69,"y":184},{"x":70,"y":184},{"x":71,"y":184},{"x":72,"y":184},{"x":72,"y":183},{"x":73,"y":183},{"x":74,"y":183},{"x":75,"y":183}],[{"x":162,"y":251},{"x":162,"y":250},{"x":161,"y":250},{"x":160,"y":249},{"x":159,"y":249},{"x":159,"y":248},{"x":158,"y":248},{"x":157,"y":247},{"x":156,"y":246},{"x":155,"y":246},{"x":154,"y":245},{"x":153,"y":245},{"x":153,"y":244},{"x":152,"y":244},{"x":151,"y":243},{"x":150,"y":243},{"x":149,"y":242},{"x":148,"y":242},{"x":147,"y":242},{"x":147,"y":241},{"x":146,"y":241},{"x":146,"y":240},{"x":145,"y":240},{"x":144,"y":240},{"x":143,"y":240},{"x":143,"y":239},{"x":142,"y":239},{"x":141,"y":238},{"x":140,"y":238},{"x":139,"y":238},{"x":138,"y":237},{"x":137,"y":237},{"x":136,"y":237},{"x":135,"y":237},{"x":134,"y":236},{"x":133,"y":236},{"x":131,"y":236},{"x":130,"y":236},{"x":129,"y":236},{"x":128,"y":236},{"x":127,"y":236},{"x":126,"y":236},{"x":125,"y":236},{"x":124,"y":237},{"x":123,"y":237},{"x":122,"y":237},{"x":121,"y":238},{"x":120,"y":238},{"x":119,"y":238},{"x":118,"y":239},{"x":117,"y":239},{"x":117,"y":240},{"x":116,"y":240},{"x":115,"y":240},{"x":115,"y":241},{"x":114,"y":241},{"x":113,"y":242},{"x":112,"y":243},{"x":111,"y":243},{"x":111,"y":244},{"x":110,"y":244},{"x":110,"y":245},{"x":109,"y":245},{"x":109,"y":246},{"x":108,"y":246},{"x":107,"y":247},{"x":107,"y":248},{"x":106,"y":249},{"x":105,"y":250},{"x":105,"y":251},{"x":104,"y":252},{"x":103,"y":253},{"x":102,"y":255},{"x":101,"y":256},{"x":101,"y":257},{"x":100,"y":259},{"x":99,"y":259},{"x":99,"y":261},{"x":98,"y":261},{"x":98,"y":262},{"x":98,"y":263},{"x":97,"y":264},{"x":97,"y":265},{"x":97,"y":266},{"x":97,"y":267},{"x":97,"y":269},{"x":97,"y":270},{"x":97,"y":271},{"x":97,"y":272},{"x":97,"y":274},{"x":97,"y":275},{"x":97,"y":277},{"x":98,"y":277},{"x":99,"y":279},{"x":99,"y":280},{"x":99,"y":281},{"x":100,"y":282},{"x":100,"y":283},{"x":101,"y":284},{"x":102,"y":285},{"x":102,"y":286},{"x":103,"y":287},{"x":103,"y":288},{"x":104,"y":288},{"x":104,"y":289},{"x":104,"y":290},{"x":105,"y":290},{"x":106,"y":291},{"x":107,"y":292},{"x":108,"y":292},{"x":108,"y":293},{"x":109,"y":293},{"x":109,"y":294},{"x":110,"y":294},{"x":111,"y":295},{"x":112,"y":295},{"x":113,"y":296},{"x":114,"y":296},{"x":115,"y":296},{"x":116,"y":297},{"x":117,"y":297},{"x":118,"y":298},{"x":119,"y":298},{"x":120,"y":298},{"x":122,"y":298},{"x":123,"y":298},{"x":125,"y":298},{"x":126,"y":298},{"x":127,"y":298},{"x":129,"y":298},{"x":131,"y":298},{"x":133,"y":298},{"x":134,"y":298},{"x":136,"y":298},{"x":138,"y":298},{"x":140,"y":298},{"x":141,"y":298},{"x":142,"y":298},{"x":144,"y":297},{"x":145,"y":297},{"x":146,"y":297},{"x":147,"y":297},{"x":148,"y":296},{"x":149,"y":296},{"x":150,"y":295},{"x":151,"y":295},{"x":152,"y":294},{"x":153,"y":294},{"x":154,"y":294},{"x":154,"y":293},{"x":155,"y":293},{"x":155,"y":292},{"x":156,"y":292},{"x":156,"y":291},{"x":157,"y":291},{"x":157,"y":290},{"x":158,"y":289},{"x":158,"y":288},{"x":159,"y":288},{"x":159,"y":287},{"x":159,"y":286},{"x":160,"y":284},{"x":160,"y":283},{"x":160,"y":281},{"x":160,"y":280},{"x":161,"y":278},{"x":161,"y":277},{"x":161,"y":275},{"x":162,"y":274},{"x":162,"y":273},{"x":162,"y":272},{"x":162,"y":271},{"x":162,"y":270},{"x":162,"y":269},{"x":162,"y":268},{"x":162,"y":267},{"x":162,"y":266},{"x":162,"y":265},{"x":162,"y":264},{"x":162,"y":263},{"x":162,"y":262},{"x":162,"y":261},{"x":162,"y":260},{"x":162,"y":259},{"x":162,"y":258},{"x":162,"y":257},{"x":161,"y":257},{"x":161,"y":256},{"x":161,"y":255},{"x":160,"y":255},{"x":160,"y":254},{"x":159,"y":254},{"x":159,"y":253},{"x":159,"y":252},{"x":158,"y":251},{"x":158,"y":250},{"x":157,"y":249},{"x":157,"y":248},{"x":156,"y":247},{"x":155,"y":247},{"x":155,"y":246},{"x":154,"y":246},{"x":154,"y":245}],[{"x":285,"y":265},{"x":283,"y":265},{"x":280,"y":264},{"x":279,"y":263},{"x":277,"y":262},{"x":275,"y":261},{"x":274,"y":261},{"x":273,"y":260},{"x":271,"y":259},{"x":270,"y":259},{"x":269,"y":259},{"x":268,"y":258},{"x":268,"y":257},{"x":267,"y":257},{"x":266,"y":257},{"x":265,"y":256},{"x":263,"y":256},{"x":263,"y":255},{"x":262,"y":255},{"x":261,"y":255},{"x":260,"y":255},{"x":260,"y":254},{"x":259,"y":254},{"x":258,"y":253},{"x":257,"y":253},{"x":256,"y":253},{"x":256,"y":252},{"x":255,"y":252},{"x":254,"y":252},{"x":253,"y":252},{"x":252,"y":252},{"x":251,"y":251},{"x":250,"y":251},{"x":249,"y":251},{"x":248,"y":251},{"x":248,"y":250},{"x":247,"y":250},{"x":246,"y":250},{"x":245,"y":250},{"x":244,"y":250},{"x":243,"y":250},{"x":242,"y":250},{"x":241,"y":250},{"x":240,"y":250},{"x":239,"y":250},{"x":238,"y":250},{"x":237,"y":250},{"x":236,"y":250},{"x":235,"y":250},{"x":234,"y":250},{"x":233,"y":250},{"x":232,"y":251},{"x":231,"y":251},{"x":230,"y":252},{"x":229,"y":252},{"x":228,"y":253},{"x":227,"y":254},{"x":226,"y":255},{"x":226,"y":256},{"x":225,"y":257},{"x":225,"y":258},{"x":225,"y":259},{"x":224,"y":260},{"x":224,"y":261},{"x":224,"y":262},{"x":224,"y":263},{"x":224,"y":264},{"x":224,"y":265},{"x":224,"y":266},{"x":224,"y":267},{"x":224,"y":268},{"x":224,"y":269},{"x":224,"y":270},{"x":224,"y":271},{"x":224,"y":272},{"x":224,"y":275},{"x":225,"y":276},{"x":226,"y":277},{"x":227,"y":280},{"x":227,"y":281},{"x":229,"y":282},{"x":229,"y":284},{"x":230,"y":285},{"x":231,"y":286},{"x":232,"y":288},{"x":232,"y":289},{"x":233,"y":291},{"x":234,"y":292},{"x":235,"y":293},{"x":235,"y":294},{"x":236,"y":295},{"x":236,"y":296},{"x":237,"y":296},{"x":237,"y":297},{"x":238,"y":298},{"x":239,"y":299},{"x":239,"y":300},{"x":240,"y":300},{"x":240,"y":301},{"x":241,"y":301},{"x":242,"y":302},{"x":243,"y":302},{"x":243,"y":303},{"x":244,"y":303},{"x":245,"y":303},{"x":246,"y":304},{"x":247,"y":304},{"x":248,"y":305},{"x":249,"y":305},{"x":250,"y":305},{"x":251,"y":305},{"x":252,"y":305},{"x":253,"y":305},{"x":255,"y":305},{"x":256,"y":305},{"x":258,"y":305},{"x":259,"y":305},{"x":260,"y":305},{"x":262,"y":305},{"x":263,"y":305},{"x":264,"y":305},{"x":266,"y":304},{"x":267,"y":303},{"x":268,"y":303},{"x":270,"y":303},{"x":272,"y":302},{"x":273,"y":302},{"x":274,"y":301},{"x":277,"y":301},{"x":278,"y":300},{"x":279,"y":299},{"x":281,"y":299},{"x":281,"y":298},{"x":282,"y":298},{"x":283,"y":297},{"x":284,"y":297},{"x":285,"y":296},{"x":286,"y":295},{"x":287,"y":295},{"x":287,"y":294},{"x":288,"y":294},{"x":289,"y":293},{"x":290,"y":293},{"x":290,"y":292},{"x":290,"y":291},{"x":291,"y":291},{"x":291,"y":290},{"x":292,"y":290},{"x":293,"y":289},{"x":293,"y":287},{"x":293,"y":286},{"x":294,"y":286},{"x":294,"y":284},{"x":294,"y":283},{"x":294,"y":282},{"x":294,"y":281},{"x":294,"y":279},{"x":294,"y":278},{"x":294,"y":276},{"x":294,"y":275},{"x":294,"y":273},{"x":294,"y":272},{"x":294,"y":271},{"x":293,"y":269},{"x":292,"y":268},{"x":292,"y":266},{"x":291,"y":266},{"x":291,"y":264},{"x":290,"y":263},{"x":289,"y":263},{"x":289,"y":262},{"x":289,"y":261},{"x":288,"y":260},{"x":287,"y":259},{"x":285,"y":258},{"x":284,"y":257},{"x":284,"y":256},{"x":283,"y":256},{"x":282,"y":256},{"x":282,"y":255},{"x":281,"y":255},{"x":279,"y":254},{"x":279,"y":253},{"x":278,"y":253},{"x":277,"y":252},{"x":275,"y":252},{"x":274,"y":251},{"x":273,"y":251},{"x":273,"y":250},{"x":272,"y":250},{"x":271,"y":250},{"x":269,"y":250},{"x":268,"y":250},{"x":267,"y":249},{"x":266,"y":249},{"x":265,"y":249},{"x":264,"y":249},{"x":263,"y":249},{"x":261,"y":249},{"x":260,"y":248},{"x":259,"y":248},{"x":258,"y":248},{"x":257,"y":248},{"x":256,"y":248},{"x":256,"y":247},{"x":255,"y":247},{"x":254,"y":247},{"x":253,"y":247},{"x":252,"y":247},{"x":251,"y":247},{"x":250,"y":247},{"x":249,"y":247},{"x":248,"y":247},{"x":247,"y":247},{"x":246,"y":247},{"x":245,"y":247},{"x":244,"y":247},{"x":243,"y":248},{"x":242,"y":248},{"x":241,"y":248},{"x":240,"y":248},{"x":239,"y":248},{"x":238,"y":248},{"x":237,"y":249},{"x":236,"y":249},{"x":235,"y":249},{"x":234,"y":249},{"x":234,"y":250},{"x":233,"y":250}],[{"x":158,"y":177},{"x":157,"y":177},{"x":159,"y":175},{"x":160,"y":173},{"x":162,"y":171},{"x":163,"y":170},{"x":165,"y":168},{"x":166,"y":167},{"x":167,"y":166},{"x":168,"y":164},{"x":169,"y":164},{"x":170,"y":162},{"x":171,"y":161},{"x":172,"y":161},{"x":173,"y":160},{"x":174,"y":159},{"x":175,"y":159},{"x":175,"y":158},{"x":176,"y":158},{"x":177,"y":157},{"x":177,"y":156},{"x":178,"y":156},{"x":178,"y":155},{"x":179,"y":155},{"x":179,"y":154},{"x":181,"y":153},{"x":181,"y":152},{"x":182,"y":152},{"x":182,"y":151},{"x":183,"y":151},{"x":184,"y":150},{"x":184,"y":149},{"x":185,"y":149},{"x":185,"y":148},{"x":186,"y":147},{"x":186,"y":146},{"x":187,"y":145},{"x":188,"y":144},{"x":188,"y":143},{"x":189,"y":143},{"x":189,"y":142},{"x":189,"y":141},{"x":190,"y":141},{"x":190,"y":140},{"x":191,"y":139},{"x":192,"y":139},{"x":192,"y":138},{"x":192,"y":137},{"x":193,"y":137},{"x":193,"y":136},{"x":194,"y":135},{"x":195,"y":134},{"x":196,"y":134},{"x":196,"y":133},{"x":197,"y":133},{"x":197,"y":132},{"x":198,"y":132},{"x":198,"y":131},{"x":199,"y":131},{"x":199,"y":130},{"x":200,"y":130},{"x":201,"y":129},{"x":202,"y":128},{"x":203,"y":128},{"x":204,"y":128},{"x":204,"y":127},{"x":205,"y":127},{"x":206,"y":126},{"x":206,"y":125},{"x":207,"y":125},{"x":208,"y":125},{"x":208,"y":124},{"x":209,"y":124},{"x":209,"y":123},{"x":210,"y":123},{"x":211,"y":123},{"x":211,"y":122},{"x":212,"y":122},{"x":212,"y":121},{"x":213,"y":121},{"x":215,"y":121},{"x":216,"y":122},{"x":218,"y":122},{"x":219,"y":122},{"x":220,"y":122},{"x":222,"y":122},{"x":223,"y":123},{"x":225,"y":123},{"x":226,"y":124},{"x":227,"y":124},{"x":229,"y":124},{"x":231,"y":124},{"x":232,"y":125},{"x":233,"y":125},{"x":234,"y":126},{"x":235,"y":126},{"x":237,"y":126},{"x":238,"y":126},{"x":239,"y":126},{"x":240,"y":126},{"x":241,"y":126},{"x":242,"y":126},{"x":243,"y":126},{"x":244,"y":126},{"x":245,"y":126},{"x":246,"y":126},{"x":248,"y":126},{"x":249,"y":126},{"x":250,"y":126},{"x":251,"y":126},{"x":252,"y":126},{"x":253,"y":126},{"x":255,"y":126},{"x":256,"y":126},{"x":257,"y":126},{"x":258,"y":126},{"x":259,"y":126},{"x":260,"y":126},{"x":261,"y":126},{"x":262,"y":126},{"x":263,"y":126},{"x":264,"y":126},{"x":261,"y":128},{"x":260,"y":129},{"x":258,"y":130},{"x":257,"y":131},{"x":256,"y":133},{"x":254,"y":134},{"x":253,"y":136},{"x":251,"y":136},{"x":250,"y":138},{"x":249,"y":139},{"x":248,"y":140},{"x":246,"y":141},{"x":245,"y":143},{"x":244,"y":144},{"x":243,"y":145},{"x":242,"y":146},{"x":241,"y":148},{"x":240,"y":148},{"x":239,"y":150},{"x":238,"y":150},{"x":236,"y":152},{"x":235,"y":153},{"x":233,"y":154},{"x":232,"y":155},{"x":230,"y":157},{"x":229,"y":159},{"x":228,"y":159},{"x":227,"y":160},{"x":226,"y":162},{"x":224,"y":163},{"x":223,"y":165},{"x":222,"y":166},{"x":221,"y":167},{"x":220,"y":167},{"x":220,"y":168},{"x":219,"y":169},{"x":218,"y":170},{"x":217,"y":170},{"x":216,"y":171},{"x":215,"y":172},{"x":215,"y":173},{"x":213,"y":173},{"x":213,"y":174},{"x":212,"y":174},{"x":211,"y":175},{"x":210,"y":176},{"x":209,"y":176},{"x":209,"y":177},{"x":208,"y":177},{"x":208,"y":178},{"x":207,"y":178},{"x":206,"y":178},{"x":206,"y":179},{"x":205,"y":179},{"x":204,"y":180},{"x":202,"y":180},{"x":201,"y":180},{"x":200,"y":180},{"x":199,"y":180},{"x":198,"y":180},{"x":197,"y":180},{"x":196,"y":180},{"x":195,"y":180},{"x":194,"y":180},{"x":193,"y":180},{"x":192,"y":180},{"x":191,"y":180},{"x":190,"y":179},{"x":189,"y":179},{"x":188,"y":179},{"x":187,"y":179},{"x":185,"y":179},{"x":184,"y":179},{"x":183,"y":179},{"x":182,"y":179},{"x":181,"y":179},{"x":180,"y":178},{"x":178,"y":178},{"x":177,"y":178},{"x":176,"y":177},{"x":175,"y":177},{"x":174,"y":177},{"x":173,"y":177},{"x":172,"y":176},{"x":171,"y":176},{"x":170,"y":176},{"x":170,"y":175},{"x":169,"y":175},{"x":169,"y":174},{"x":168,"y":174},{"x":167,"y":174},{"x":166,"y":173},{"x":165,"y":173},{"x":164,"y":172},{"x":163,"y":172},{"x":162,"y":172},{"x":161,"y":172}],[{"x":269,"y":133},{"x":267,"y":135},{"x":266,"y":136},{"x":264,"y":137},{"x":263,"y":139},{"x":262,"y":139},{"x":261,"y":141},{"x":260,"y":141},{"x":259,"y":142},{"x":259,"y":143},{"x":258,"y":144},{"x":257,"y":144},{"x":256,"y":145},{"x":255,"y":146},{"x":255,"y":147},{"x":254,"y":147},{"x":253,"y":148},{"x":252,"y":149},{"x":251,"y":151},{"x":250,"y":152},{"x":249,"y":153},{"x":249,"y":154},{"x":248,"y":154},{"x":248,"y":155},{"x":247,"y":155},{"x":247,"y":156},{"x":247,"y":157},{"x":246,"y":157},{"x":245,"y":158},{"x":245,"y":159},{"x":244,"y":159},{"x":244,"y":160},{"x":243,"y":160},{"x":243,"y":161},{"x":242,"y":163},{"x":241,"y":163},{"x":241,"y":164},{"x":240,"y":164},{"x":239,"y":165},{"x":238,"y":165},{"x":238,"y":166},{"x":237,"y":167},{"x":236,"y":167},{"x":236,"y":168},{"x":235,"y":168},{"x":234,"y":168},{"x":234,"y":169},{"x":233,"y":169},{"x":233,"y":170},{"x":232,"y":170},{"x":231,"y":171},{"x":230,"y":171},{"x":229,"y":172},{"x":228,"y":172},{"x":227,"y":172},{"x":227,"y":173},{"x":226,"y":173},{"x":226,"y":174},{"x":225,"y":174},{"x":225,"y":175},{"x":224,"y":175},{"x":224,"y":176},{"x":223,"y":176},{"x":222,"y":177},{"x":221,"y":177},{"x":221,"y":178},{"x":220,"y":178},{"x":220,"y":179}],[{"x":269,"y":134},{"x":270,"y":133},{"x":272,"y":133},{"x":275,"y":133},{"x":277,"y":133},{"x":279,"y":133},{"x":280,"y":133},{"x":282,"y":133},{"x":284,"y":133},{"x":285,"y":133},{"x":287,"y":133},{"x":288,"y":133},{"x":289,"y":133},{"x":290,"y":133},{"x":291,"y":133},{"x":292,"y":133},{"x":293,"y":133},{"x":294,"y":133},{"x":295,"y":133},{"x":296,"y":133},{"x":297,"y":133},{"x":298,"y":133},{"x":299,"y":133},{"x":300,"y":133},{"x":301,"y":133},{"x":302,"y":133},{"x":303,"y":133},{"x":303,"y":134},{"x":303,"y":135},{"x":304,"y":136},{"x":304,"y":137},{"x":304,"y":138},{"x":304,"y":139},{"x":304,"y":140},{"x":304,"y":141},{"x":304,"y":142},{"x":304,"y":143},{"x":304,"y":144},{"x":304,"y":145},{"x":303,"y":146},{"x":303,"y":147},{"x":303,"y":148},{"x":303,"y":149},{"x":303,"y":150},{"x":303,"y":151},{"x":302,"y":151},{"x":302,"y":152},{"x":302,"y":154},{"x":302,"y":155},{"x":302,"y":157},{"x":301,"y":157},{"x":301,"y":158},{"x":301,"y":159},{"x":300,"y":160},{"x":300,"y":161},{"x":300,"y":163},{"x":299,"y":165},{"x":299,"y":166},{"x":298,"y":167},{"x":298,"y":168},{"x":298,"y":169},{"x":298,"y":170},{"x":298,"y":171},{"x":298,"y":172},{"x":298,"y":173},{"x":297,"y":173},{"x":297,"y":174},{"x":297,"y":175},{"x":297,"y":176},{"x":297,"y":177},{"x":297,"y":178},{"x":297,"y":179},{"x":297,"y":180},{"x":297,"y":181},{"x":297,"y":182},{"x":297,"y":183},{"x":297,"y":184},{"x":297,"y":185},{"x":297,"y":186},{"x":297,"y":187},{"x":297,"y":188},{"x":297,"y":189},{"x":297,"y":190},{"x":297,"y":191},{"x":297,"y":192},{"x":297,"y":193},{"x":297,"y":194},{"x":295,"y":194},{"x":294,"y":194},{"x":293,"y":194},{"x":291,"y":194},{"x":289,"y":194},{"x":287,"y":194},{"x":286,"y":193},{"x":283,"y":192},{"x":282,"y":192},{"x":279,"y":191},{"x":277,"y":190},{"x":274,"y":189},{"x":269,"y":187},{"x":266,"y":186},{"x":263,"y":186},{"x":261,"y":185},{"x":260,"y":184},{"x":258,"y":184},{"x":257,"y":184},{"x":256,"y":183},{"x":254,"y":183},{"x":253,"y":183},{"x":252,"y":182},{"x":250,"y":182},{"x":249,"y":182},{"x":248,"y":182},{"x":246,"y":181},{"x":244,"y":180},{"x":243,"y":180},{"x":242,"y":180},{"x":241,"y":179},{"x":240,"y":179},{"x":239,"y":179},{"x":238,"y":179},{"x":238,"y":178},{"x":237,"y":178},{"x":236,"y":178},{"x":235,"y":177},{"x":234,"y":177},{"x":233,"y":177},{"x":232,"y":177},{"x":231,"y":177},{"x":230,"y":177},{"x":229,"y":177},{"x":228,"y":177},{"x":227,"y":177},{"x":226,"y":177},{"x":225,"y":177},{"x":224,"y":177},{"x":223,"y":177},{"x":222,"y":177}],[{"x":269,"y":134},{"x":270,"y":133},{"x":272,"y":133},{"x":275,"y":133},{"x":277,"y":133},{"x":279,"y":133},{"x":280,"y":133},{"x":282,"y":133},{"x":284,"y":133},{"x":285,"y":133},{"x":287,"y":133},{"x":288,"y":133},{"x":289,"y":133},{"x":290,"y":133},{"x":291,"y":133},{"x":292,"y":133},{"x":293,"y":133},{"x":294,"y":133},{"x":295,"y":133},{"x":296,"y":133},{"x":297,"y":133},{"x":298,"y":133},{"x":299,"y":133},{"x":300,"y":133},{"x":301,"y":133},{"x":302,"y":133},{"x":303,"y":133},{"x":303,"y":134},{"x":303,"y":135},{"x":304,"y":136},{"x":304,"y":137},{"x":304,"y":138},{"x":304,"y":139},{"x":304,"y":140},{"x":304,"y":141},{"x":304,"y":142},{"x":304,"y":143},{"x":304,"y":144},{"x":304,"y":145},{"x":303,"y":146},{"x":303,"y":147},{"x":303,"y":148},{"x":303,"y":149},{"x":303,"y":150},{"x":303,"y":151},{"x":302,"y":151},{"x":302,"y":152},{"x":302,"y":154},{"x":302,"y":155},{"x":302,"y":157},{"x":301,"y":157},{"x":301,"y":158},{"x":301,"y":159},{"x":300,"y":160},{"x":300,"y":161},{"x":300,"y":163},{"x":299,"y":165},{"x":299,"y":166},{"x":298,"y":167},{"x":298,"y":168},{"x":298,"y":169},{"x":298,"y":170},{"x":298,"y":171},{"x":298,"y":172},{"x":298,"y":173},{"x":297,"y":173},{"x":297,"y":174},{"x":297,"y":175},{"x":297,"y":176},{"x":297,"y":177},{"x":297,"y":178},{"x":297,"y":179},{"x":297,"y":180},{"x":297,"y":181},{"x":297,"y":182},{"x":297,"y":183},{"x":297,"y":184},{"x":297,"y":185},{"x":297,"y":186},{"x":297,"y":187},{"x":297,"y":188},{"x":297,"y":189},{"x":297,"y":190},{"x":297,"y":191},{"x":297,"y":192},{"x":297,"y":193},{"x":297,"y":194},{"x":295,"y":194},{"x":294,"y":194},{"x":293,"y":194},{"x":291,"y":194},{"x":289,"y":194},{"x":287,"y":194},{"x":286,"y":193},{"x":283,"y":192},{"x":282,"y":192},{"x":279,"y":191},{"x":277,"y":190},{"x":274,"y":189},{"x":269,"y":187},{"x":266,"y":186},{"x":263,"y":186},{"x":261,"y":185},{"x":260,"y":184},{"x":258,"y":184},{"x":257,"y":184},{"x":256,"y":183},{"x":254,"y":183},{"x":253,"y":183},{"x":252,"y":182},{"x":250,"y":182},{"x":249,"y":182},{"x":248,"y":182},{"x":246,"y":181},{"x":244,"y":180},{"x":243,"y":180},{"x":242,"y":180},{"x":241,"y":179},{"x":240,"y":179},{"x":239,"y":179},{"x":238,"y":179},{"x":238,"y":178},{"x":237,"y":178},{"x":236,"y":178},{"x":235,"y":177},{"x":234,"y":177},{"x":233,"y":177},{"x":232,"y":177},{"x":231,"y":177},{"x":230,"y":177},{"x":229,"y":177},{"x":228,"y":177},{"x":227,"y":177},{"x":226,"y":177},{"x":225,"y":177},{"x":224,"y":177},{"x":223,"y":177},{"x":222,"y":177}]]}